plone.multilingualbehavior-1.2.3-py2.7-nspkg.pth
plone/multilingualbehavior/__init__.py
plone/multilingualbehavior/cloner.py
plone/multilingualbehavior/configure.zcml
plone/multilingualbehavior/directives.py
plone/multilingualbehavior/form.py
plone/multilingualbehavior/interfaces.py
plone/multilingualbehavior/language.py
plone/multilingualbehavior/meta.py
plone/multilingualbehavior/meta.zcml
plone/multilingualbehavior/profile.zcml
plone/multilingualbehavior/schemaeditor.py
plone/multilingualbehavior/setuphandlers.py
plone/multilingualbehavior/subscriber.py
plone/multilingualbehavior/supermodel.py
plone/multilingualbehavior/testing.py
plone/multilingualbehavior/utils.py
plone/multilingualbehavior/Extensions/__init__.py
plone/multilingualbehavior/Extensions/install.py
plone/multilingualbehavior/profiles/default/componentregistry.xml
plone/multilingualbehavior/profiles/default/metadata.xml
plone/multilingualbehavior/profiles/uninstall/componentregistry.xml
plone/multilingualbehavior/profiles/uninstall/import_steps.xml
plone/multilingualbehavior/profiles/uninstall/pmb_uninstall.txt
plone/multilingualbehavior/tests/__init__.py
plone/multilingualbehavior/tests/configure.zcml
plone/multilingualbehavior/tests/doctest_behavior.txt
plone/multilingualbehavior/tests/doctest_grok_directive.txt
plone/multilingualbehavior/tests/doctest_manualbehavior.txt
plone/multilingualbehavior/tests/doctest_native.txt
plone/multilingualbehavior/tests/language.txt
plone/multilingualbehavior/tests/samplecontent_type.xml
plone/multilingualbehavior/tests/schemata.py
plone/multilingualbehavior/tests/tests.py
plone/multilingualbehavior/tests/profile/.DS_Store
plone/multilingualbehavior/tests/profile/metadata.xml
plone/multilingualbehavior/tests/profile/types.xml
plone/multilingualbehavior/tests/profile/types/samplecontent.xml
plone/multilingualbehavior/tests/profile/types/samplecontent_nobehavior.xml
plone/multilingualbehavior/tests/profile/types/testtypegrok.xml
plone.multilingualbehavior-1.2.3.dist-info/METADATA
plone.multilingualbehavior-1.2.3.dist-info/WHEEL
plone.multilingualbehavior-1.2.3.dist-info/entry_points.txt
plone.multilingualbehavior-1.2.3.dist-info/namespace_packages.txt
plone.multilingualbehavior-1.2.3.dist-info/top_level.txt
plone.multilingualbehavior-1.2.3.dist-info/RECORD
