Metadata-Version: 2.1
Name: plone.multilingualbehavior
Version: 1.2.3
Summary: Dexterity behavior for enabling multilingual extensions
Home-page: https://github.com/plone/plone.multilingualbehavior
Author: Plone Foundation
Author-email: sneridagh@gmail.com
License: GPL
Keywords: dexterity multilingual plone
Platform: UNKNOWN
Classifier: Development Status :: 7 - Inactive
Classifier: Framework :: Plone
Classifier: Framework :: Plone :: 4.3
Classifier: License :: OSI Approved :: GNU General Public License (GPL)
Classifier: Programming Language :: Python
Classifier: Programming Language :: Python :: 2
Classifier: Programming Language :: Python :: 2.7
Requires-Dist: setuptools
Requires-Dist: plone.directives.form
Requires-Dist: plone.directives.dexterity
Requires-Dist: plone.app.dexterity
Requires-Dist: plone.multilingual
Requires-Dist: plone.app.multilingual
Provides-Extra: test
Requires-Dist: plone.app.testing ; extra == 'test'
Requires-Dist: plone.app.dexterity[relations] ; extra == 'test'
